LICENSE
MANIFEST.in
README.rst
pytest_djangorestframework.py
setup.py
pytest_djangorestframework.egg-info/PKG-INFO
pytest_djangorestframework.egg-info/SOURCES.txt
pytest_djangorestframework.egg-info/dependency_links.txt
pytest_djangorestframework.egg-info/entry_points.txt
pytest_djangorestframework.egg-info/requires.txt
pytest_djangorestframework.egg-info/top_level.txt