Metadata-Version: 1.2
Name: pytest-djangorestframework
Version: 0.1.2
Summary: A djangorestframework plugin for pytest
Home-page: https://github.com/eduzen/pytest-djangorestframework
Author: Eduardo Enriquez
Author-email: eduardo.a.enriquez@gmail.com
Maintainer: Eduardo Enriquez
Maintainer-email: eduardo.a.enriquez@gmail.com
License: BSD-3
Platform: UNKNOWN
Classifier: Development Status :: 4 - Beta
Classifier: Framework :: Pytest
Classifier: Intended Audience :: Developers
Classifier: Topic :: Software Development :: Testing
Classifier: Programming Language :: Python
Classifier: Programming Language :: Python :: 2
Classifier: Programming Language :: Python :: 2.7
Classifier: Programming Language :: Python :: 3
Classifier: Programming Language :: Python :: 3.4
Classifier: Programming Language :: Python :: 3.5
Classifier: Programming Language :: Python :: 3.6
Classifier: Programming Language :: Python :: 3.7
Classifier: Programming Language :: Python :: Implementation :: CPython
Classifier: Programming Language :: Python :: Implementation :: PyPy
Classifier: Operating System :: OS Independent
Classifier: License :: OSI Approved :: BSD License
Requires-Python: >=2.7, !=3.0.*, !=3.1.*, !=3.2.*, !=3.3.*
